[{"lobs":[{"lineOfBusiness":"COMRLENDING","businessEntityName":[],"subEntity":["AUD"]}],"rateType":"SPOT","fromCurrency":"AUD","toCurrency":"CAD","buyRate":0.012185525107178,"midRate":0.012180549854382,"sellRate":0.153366705928543,"effectiveDate":"2018-04-15"},{"lobs":[{"lineOfBusiness":"COMRLENDING","businessEntityName":[],"subEntity":["AUD"]}],"rateType":"SPOT","fromCurrency":"AUD","toCurrency":"NZD","buyRate":1.000060003600216,"midRate":1.000060003600216,"sellRate":12.580198767140521,"effectiveDate":"2018-04-15"},{"lobs":[{"lineOfBusiness":"COMRLENDING","businessEntityName":[],"subEntity":["AUD"]}],"rateType":"SPOT","fromCurrency":"AUD","toCurrency":"DKK","buyRate":0.012187140860193,"midRate":0.012182029241012,"sellRate":0.211720867208672,"effectiveDate":"2018-04-15"},{"lobs":[{"lineOfBusiness":"COMRLENDING","businessEntityName":[],"subEntity":["AUD"]}],"rateType":"SPOT","fromCurrency":"AUD","toCurrency":"CNH","buyRate":0.012187543380037,"midRate":0.012182432907383,"sellRate":0.20190273134015,"effectiveDate":"2018-04-15"},{"lobs":[{"lineOfBusiness":"COMRLENDING","businessEntityName":[],"subEntity":["AUD"]}],"rateType":"SPOT","fromCurrency":"AUD","toCurrency":"NOK","buyRate":0.012187274535421,"midRate":0.01218216428818,"sellRate":0.162253374870197,"effectiveDate":"2018-04-15"},{"lobs":[{"lineOfBusiness":"COMRLENDING","businessEntityName":[],"subEntity":["AUD"]}],"rateType":"SPOT","fromCurrency":"AUD","toCurrency":"CHF","buyRate":0.012187678549491,"midRate":0.012182566479352,"sellRate":1.398679646413785,"effectiveDate":"2018-04-15"},{"lobs":[{"lineOfBusiness":"COMRLENDING","businessEntityName":[],"subEntity":["AUD"]}],"rateType":"SPOT","fromCurrency":"AUD","toCurrency":"MXN","buyRate":0.012186332930128,"midRate":0.012181221988519,"sellRate":0.068414801679173,"effectiveDate":"2018-04-15"},{"lobs":[{"lineOfBusiness":"COMRLENDING","businessEntityName":[],"subEntity":["AUD"]}],"rateType":"SPOT","fromCurrency":"AUD","toCurrency":"GBP","buyRate":0.999910008099271,"midRate":0.999910008099271,"sellRate":1.749995625010937,"effectiveDate":"2018-04-15"},{"lobs":[{"lineOfBusiness":"COMRLENDING","businessEntityName":[],"subEntity":["AUD"]}],"rateType":"SPOT","fromCurrency":"AUD","toCurrency":"HKD","buyRate":0.012186468072733,"midRate":0.012181357017789,"sellRate":0.177834684876938,"effectiveDate":"2018-04-15"},{"lobs":[{"lineOfBusiness":"COMRLENDING","businessEntityName":[],"subEntity":["AUD"]}],"rateType":"SPOT","fromCurrency":"AUD","toCurrency":"ZAR","buyRate":0.01218619779052,"midRate":0.012181088446031,"sellRate":0.098502758077226,"effectiveDate":"2018-04-15"},{"lobs":[{"lineOfBusiness":"COMRLENDING","businessEntityName":[],"subEntity":["AUD"]}],"rateType":"SPOT","fromCurrency":"AUD","toCurrency":"THB","buyRate":0.012185660231866,"midRate":0.01218041632663,"sellRate":0.153468385512584,"effectiveDate":"2018-04-15"},{"lobs":[{"lineOfBusiness":"COMRLENDING","businessEntityName":[],"subEntity":["AUD"]}],"rateType":"SPOT","fromCurrency":"AUD","toCurrency":"CZK","buyRate":0.012185391470323,"midRate":0.012180281318213,"sellRate":0.153344599049877,"effectiveDate":"2018-04-15"},{"lobs":[{"lineOfBusiness":"COMRLENDING","businessEntityName":[],"subEntity":["AUD"]}],"rateType":"SPOT","fromCurrency":"AUD","toCurrency":"USD","buyRate":0.110389897116616,"midRate":0.11036674870595,"sellRate":1.388888888888889,"effectiveDate":"2018-04-15"},{"lobs":[{"lineOfBusiness":"COMRLENDING","businessEntityName":[],"subEntity":["AUD"]}],"rateType":"SPOT","fromCurrency":"AUD","toCurrency":"SGD","buyRate":0.012187409698911,"midRate":0.012182297854259,"sellRate":1.013787510137875,"effectiveDate":"2018-04-15"},{"lobs":[{"lineOfBusiness":"COMRLENDING","businessEntityName":[],"subEntity":["AUD"]}],"rateType":"SPOT","fromCurrency":"AUD","toCurrency":"CNY","buyRate":0.012186064138911,"midRate":0.012180953422714,"sellRate":0.20187338501292,"effectiveDate":"2018-04-15"},{"lobs":[{"lineOfBusiness":"COMRLENDING","businessEntityName":[],"subEntity":["AUD"]}],"rateType":"SPOT","fromCurrency":"AUD","toCurrency":"EUR","buyRate":0.999920006399488,"midRate":0.999920006399488,"sellRate":1.569439866911499,"effectiveDate":"2018-04-15"},{"lobs":[{"lineOfBusiness":"COMRLENDING","businessEntityName":[],"subEntity":["AUD"]}],"rateType":"SPOT","fromCurrency":"AUD","toCurrency":"IDR","buyRate":0.01218673688177,"midRate":0.012181492050054,"sellRate":0.009578544061303,"effectiveDate":"2018-04-15"},{"lobs":[{"lineOfBusiness":"COMRLENDING","businessEntityName":[],"subEntity":["AUD"]}],"rateType":"SPOT","fromCurrency":"AUD","toCurrency":"SEK","buyRate":0.012185795359552,"midRate":0.012180684868751,"sellRate":0.153366705928543,"effectiveDate":"2018-04-15"},{"lobs":[{"lineOfBusiness":"COMRLENDING","businessEntityName":[],"subEntity":["AUD"]}],"rateType":"SPOT","fromCurrency":"AUD","toCurrency":"JPY","buyRate":0.012186601733203,"midRate":0.012181625601392,"sellRate":0.01222613458529,"effectiveDate":"2018-04-15"}]