[{"fromCurrency": "EUR", "toCurrency": "CHF", "buyRate": 0.009881661178392, "midRate": 0.008138687797739, "sellRate": 0.006875859654353, "effectiveDate": "2021-10-16", "rateType": "SPOT", "lobs": [{"lineOfBusiness": "COMRLENDING", "businessEntityName": ["AUSTRALIA"], "subEntity": ["EUR"]}]},{"fromCurrency": "EUR", "toCurrency": "CNH", "buyRate": 0.009881562555676, "midRate": 0.008138614273957, "sellRate": 0.00687580244912, "effectiveDate": "2021-10-16", "rateType": "SPOT", "lobs": [{"lineOfBusiness": "COMRLENDING", "businessEntityName": ["AUSTRALIA"], "subEntity": ["EUR"]}]},{"fromCurrency": "EUR", "toCurrency": "SGD", "buyRate": 0.009881463934929, "midRate": 0.008138540089146, "sellRate": 0.006875745244838, "effectiveDate": "2021-10-16", "rateType": "SPOT", "lobs": [{"lineOfBusiness": "COMRLENDING", "businessEntityName": ["AUSTRALIA"], "subEntity": ["EUR"]}]},{"fromCurrency": "EUR", "toCurrency": "NOK", "buyRate": 0.009881366292565, "midRate": 0.008138466568034, "sellRate": 0.006875688514259, "effectiveDate": "2021-10-16", "rateType": "SPOT", "lobs": [{"lineOfBusiness": "COMRLENDING", "businessEntityName": ["AUSTRALIA"], "subEntity": ["EUR"]}]},{"fromCurrency": "EUR", "toCurrency": "DKK", "buyRate": 0.009881267675735, "midRate": 0.00813839304825, "sellRate": 0.006875631311873, "effectiveDate": "2021-10-16", "rateType": "SPOT", "lobs": [{"lineOfBusiness": "COMRLENDING", "businessEntityName": ["AUSTRALIA"], "subEntity": ["EUR"]}]},{"fromCurrency": "EUR", "toCurrency": "GBP", "buyRate": 0.999990000099999, "midRate": 0.995490428359531, "sellRate": 0.999990000099999, "effectiveDate": "2021-10-16", "rateType": "SPOT", "lobs": [{"lineOfBusiness": "COMRLENDING", "businessEntityName": ["AUSTRALIA"], "subEntity": ["EUR"]}]},{"fromCurrency": "EUR", "toCurrency": "USD", "buyRate": 0.099403578528827, "midRate": 0.09000900090009, "sellRate": 0.082918739635158, "effectiveDate": "2021-10-16", "rateType": "SPOT", "lobs": [{"lineOfBusiness": "COMRLENDING", "businessEntityName": ["AUSTRALIA"], "subEntity": ["EUR"]}]},{"fromCurrency": "EUR", "toCurrency": "IDR", "buyRate": 0.009880972813393, "midRate": 0.008138098982396, "sellRate": 0.006875460183144, "effectiveDate": "2021-10-16", "rateType": "SPOT", "lobs": [{"lineOfBusiness": "COMRLENDING", "businessEntityName": ["AUSTRALIA"], "subEntity": ["EUR"]}]},{"fromCurrency": "EUR", "toCurrency": "JPY", "buyRate": 0.009880875180734, "midRate": 0.008138172496867, "sellRate": 0.006875403457269, "effectiveDate": "2021-10-16", "rateType": "SPOT", "lobs": [{"lineOfBusiness": "COMRLENDING", "businessEntityName": ["AUSTRALIA"], "subEntity": ["EUR"]}]},{"fromCurrency": "EUR", "toCurrency": "MXN", "buyRate": 0.009880678944925, "midRate": 0.008137951957438, "sellRate": 0.006875346259626, "effectiveDate": "2021-10-16", "rateType": "SPOT", "lobs": [{"lineOfBusiness": "COMRLENDING", "businessEntityName": ["AUSTRALIA"], "subEntity": ["EUR"]}]},{"fromCurrency": "EUR", "toCurrency": "ZAR", "buyRate": 0.009880580341815, "midRate": 0.008137878446951, "sellRate": 0.006875289535631, "effectiveDate": "2021-10-16", "rateType": "SPOT", "lobs": [{"lineOfBusiness": "COMRLENDING", "businessEntityName": ["AUSTRALIA"], "subEntity": ["EUR"]}]},{"fromCurrency": "EUR", "toCurrency": "HKD", "buyRate": 0.009880776573706, "midRate": 0.008138025469253, "sellRate": 0.006875232339883, "effectiveDate": "2021-10-16", "rateType": "SPOT", "lobs": [{"lineOfBusiness": "COMRLENDING", "businessEntityName": ["AUSTRALIA"], "subEntity": ["EUR"]}]},{"fromCurrency": "EUR", "toCurrency": "CNY", "buyRate": 0.009880481740672, "midRate": 0.008137804275554, "sellRate": 0.006875175145087, "effectiveDate": "2021-10-16", "rateType": "SPOT", "lobs": [{"lineOfBusiness": "COMRLENDING", "businessEntityName": ["AUSTRALIA"], "subEntity": ["EUR"]}]},{"fromCurrency": "EUR", "toCurrency": "AUD", "buyRate": 1.010009191083639, "midRate": 0.078757893509877, "sellRate": 1.008349130803049, "effectiveDate": "2021-10-16", "rateType": "SPOT", "lobs": [{"lineOfBusiness": "COMRLENDING", "businessEntityName": ["AUSTRALIA"], "subEntity": ["EUR"]}]},{"fromCurrency": "EUR", "toCurrency": "SEK", "buyRate": 0.009880285520491, "midRate": 0.008137657261244, "sellRate": 0.006875061231014, "effectiveDate": "2021-10-16", "rateType": "SPOT", "lobs": [{"lineOfBusiness": "COMRLENDING", "businessEntityName": ["AUSTRALIA"], "subEntity": ["EUR"]}]},{"fromCurrency": "EUR", "toCurrency": "CAD", "buyRate": 0.009880089308103, "midRate": 0.008137583756081, "sellRate": 0.006875004511722, "effectiveDate": "2021-10-16", "rateType": "SPOT", "lobs": [{"lineOfBusiness": "COMRLENDING", "businessEntityName": ["AUSTRALIA"], "subEntity": ["EUR"]}]},{"fromCurrency": "EUR", "toCurrency": "THB", "buyRate": 0.009880187901414, "midRate": 0.008137510252246, "sellRate": 0.006874947320716, "effectiveDate": "2021-10-16", "rateType": "SPOT", "lobs": [{"lineOfBusiness": "COMRLENDING", "businessEntityName": ["AUSTRALIA"], "subEntity": ["EUR"]}]},{"fromCurrency": "EUR", "toCurrency": "CZK", "buyRate": 0.009879990716761, "midRate": 0.008137436749739, "sellRate": 0.006874890130662, "effectiveDate": "2021-10-16", "rateType": "SPOT", "lobs": [{"lineOfBusiness": "COMRLENDING", "businessEntityName": ["AUSTRALIA"], "subEntity": ["EUR"]}]},{"fromCurrency": "EUR", "toCurrency": "NZD", "buyRate": 1.000120014401728, "midRate": 0.995609362710447, "sellRate": 1.000100010001, "effectiveDate": "2021-10-16", "rateType": "SPOT", "lobs": [{"lineOfBusiness": "COMRLENDING", "businessEntityName": ["AUSTRALIA"], "subEntity": ["EUR"]}]}]