{"selectionCriteria":[{"criterionName":"zone","criterionValue":"EUR"}],"productFileName":"VLS_DB_CONNECTION.csv","controlInfo":{"fileName":"CCB_LIQ_EUR_VLS_DB_CONNECTION_20211102.csv","dateCreated":"2020-11-25 05:52:08","loadAssurance":[{"name":"total","elementValue":2,"elementType":"CountOfRecords"}],"size":587,"isEncrypted":false,"dateRecordStart":"","checksum":"f9f8870702f7b0038ec5259c4161ad8c","encryptionType":"","hashingAlgorithm":"MD5","dateRecordEnd":"2020-11-25 12:46:23"},"platformFileName":"CCB_LIQ_EUR_VLS_DB_CONNECTION_20211102.csv","metadataInfo":{"keyFieldNames":["DBC_RID_DB_CONNECT"],"name":"VLS_DB_CONNECTION","fields":[{"fieldName":"DBC_RID_DB_CONNECT","nullable":false,"dataType":"CHARACTER","length":8},{"fieldName":"DBC_XID_USER_ID","nullable":false,"dataType":"CHARACTER","length":32},{"fieldName":"DBC_CHR_PASSWORD","nullable":false,"dataType":"CHARACTER","length":80},{"fieldName":"DBC_TXT_COMMENT","nullable":false,"dataType":"VARCHAR","length":128},{"fieldName":"DBC_TSP_REC_CREATE","nullable":false,"dataType":"TIMESTAMP","length":19,"fieldDescription":"Timestamp from when this row was created."},{"fieldName":"DBC_TSP_REC_UPDATE","nullable":false,"dataType":"TIMESTAMP","length":19,"fieldDescription":"Timestamp from when this row was last updated."},{"fieldName":"DBC_UID_REC_CREATE","nullable":false,"dataType":"CHARACTER","length":8,"fieldDescription":"User ID that created this row.  This is a foreign key to VLS_USER_PROFILE.UPT_UID_USERID."},{"fieldName":"DBC_UID_REC_UPDATE","nullable":false,"dataType":"CHARACTER","length":8,"fieldDescription":"User ID that last updated this row.  This is a foreign key to VLS_USER_PROFILE.UPT_UID_USERID."}],"version":"1.0.0.0","parentProduct":{"name":"COMRLENDING","version":"7.5.1.2"}},"version":"1.0.0.1"}