{"selectionCriteria":[{"criterionName":"zone","criterionValue":"EUR"}],"productFileName":"VLS_GEN_COMMENT.csv","controlInfo":{"fileName":"CCB_LIQ_EUR_VLS_GEN_COMMENT_20211102.csv","dateCreated":"2020-11-25 05:52:10","loadAssurance":[{"name":"total","elementValue":72,"elementType":"CountOfRecords"}],"size":13768,"isEncrypted":false,"dateRecordStart":"","checksum":"4a0194d549f18186a589a26e8738f380","encryptionType":"","hashingAlgorithm":"MD5","dateRecordEnd":"2020-11-25 12:46:23"},"platformFileName":"CCB_LIQ_EUR_VLS_GEN_COMMENT_20211102.csv","metadataInfo":{"keyFieldNames":["CMT_RID_COMMENT"],"name":"VLS_GEN_COMMENT","fields":[{"fieldName":"CMT_RID_COMMENT","nullable":false,"dataType":"CHARACTER","length":8,"fieldDescription":"The Record ID (RID) that uniquely identifies this comment."},{"fieldName":"CMT_UID_AUTHOR","nullable":true,"dataType":"CHARACTER","length":8,"fieldDescription":"The User ID of the person who created the comment."},{"fieldName":"CMT_TSP_REC_CREATE","nullable":false,"dataType":"TIMESTAMP","length":19,"fieldDescription":"Timestamp from when this row was created."},{"fieldName":"CMT_TSP_REC_UPDATE","nullable":false,"dataType":"TIMESTAMP","length":19,"fieldDescription":"Timestamp from when this row was last updated."},{"fieldName":"CMT_UID_REC_CREATE","nullable":false,"dataType":"CHARACTER","length":8,"fieldDescription":"User ID that created this row.  This is a foreign key to VLS_USER_PROFILE.UPT_UID_USERID."},{"fieldName":"CMT_UID_REC_UPDATE","nullable":false,"dataType":"CHARACTER","length":8,"fieldDescription":"User ID that last updated this row.  This is a foreign key to VLS_USER_PROFILE.UPT_UID_USERID."},{"fieldName":"CMT_CDE_CMT_SUBTYP","nullable":true,"dataType":"CHARACTER","length":5,"fieldDescription":"The comment subtype code."},{"fieldName":"CMT_TID_TABLE_ID","nullable":false,"dataType":"CHARACTER","length":3,"fieldDescription":"The Record ID (RID) of the entity\/table associated with this comment."},{"fieldName":"CMT_RID_GENRIC_KEY","nullable":false,"dataType":"CHARACTER","length":8,"fieldDescription":"The Record ID (RID) for the generic key."},{"fieldName":"CMT_PID_DEAL","nullable":true,"dataType":"CHARACTER","length":8,"fieldDescription":"The Record ID (RID) for the deal."},{"fieldName":"CMT_CID_CUST_ID","nullable":true,"dataType":"CHARACTER","length":8,"fieldDescription":"The Record ID (RID) for the customer."},{"fieldName":"CMT_TXT_TTL_CMNT","nullable":false,"dataType":"VARCHAR","length":40,"fieldDescription":"The title associated with the comment subject."},{"fieldName":"CMT_TXT_COMMENT","nullable":false,"dataType":"VARCHAR","length":3500,"fieldDescription":"The comment text."},{"fieldName":"CMT_CDE_BRANCH","nullable":true,"dataType":"CHARACTER","length":5,"fieldDescription":"The Branch Identifier"}],"version":"1.0.0.0","parentProduct":{"name":"COMRLENDING","version":"7.5.1.2"}},"version":"1.0.0.1"}